{"AWB": [8, "/tags/awb/", {"posts": [{"date": "08/15/2017", "isodate": "2017-08-15T15:24:13+02:00", "title": "After-Work-Beer im August", "url": "/announcements/2017/after-work-beer-im-august/"}, {"date": "07/05/2017", "isodate": "2017-07-05T11:51:32+02:00", "title": "After-Work-Beer im Juli", "url": "/announcements/2017/after-work-beer-im-juli/"}, {"date": "04/25/2017", "isodate": "2017-04-25T17:51:32+02:00", "title": "After-Work-Beer im Mai", "url": "/announcements/2017/after-work-beer-im-mai/"}, {"date": "02/16/2017", "isodate": "2017-02-16T18:53:27+01:00", "title": "After-Work-Beer im Februar mit Vortrag zum Thema HAMNET", "url": "/announcements/2017/after-work-beer-im-februar-mit-vortrag-zum-thema-hamnet/"}, {"date": "11/28/2016", "isodate": "2016-11-28T17:04:11+01:00", "title": "After-Work-Beer im November", "url": "/announcements/2016/awb-november/"}, {"date": "09/28/2016", "isodate": "2016-09-28T12:24:55+02:00", "title": "After-Work-Beer im Oktober", "url": "/announcements/2016/awb-oktober/"}, {"date": "07/14/2016", "isodate": "2016-07-14T09:32:00+02:00", "title": "After-Work-Beer im August", "url": "/announcements/2016/awb-august/"}, {"date": "07/07/2016", "isodate": "2016-07-07T10:30:27+02:00", "title": "After-Work-Beer im Juli", "url": "/announcements/2016/awb-july/"}]}], "MBA": [1, "/tags/mba/", {"posts": [{"date": "07/06/2016", "isodate": "2016-07-06T18:36:15+02:00", "title": "Ank\u00fcndigung: Modellberatungsabend 2016", "url": "/announcements/2016/mba/"}]}], "RSEC": [1, "/tags/rsec/", {"posts": [{"date": "06/27/2016", "isodate": "2016-06-27T18:02:58+02:00", "title": "Team des KIT gewinnt R&S Engingeering Competition 2016", "url": "/reports/2016/rs-challenge/"}]}], "SPC": [1, "/tags/spc/", {"posts": [{"date": "04/21/2016", "isodate": "2016-04-21T17:52:18+02:00", "title": "Stefan Wunsch gewinnt den Region 8 Student Paper Contest 2016", "url": "/reports/2016/spc/"}]}], "isic": [8, "/tags/isic/", {"posts": [{"date": "11/15/2017", "isodate": "2017-11-15T23:17:46.938870+01:00", "title": "Signal Intelligence Challenge 2017", "url": "/events/sigint-challenge/"}, {"date": "11/15/2017", "isodate": "2017-11-15T18:53:56+01:00", "title": "ISIC17 Siegerehrung beim Thanksgiving Event", "url": "/announcements/2017/isic17-siegerehrung-thanksgiving/"}, {"date": "11/10/2017", "isodate": "2017-11-10T09:37:13+01:00", "title": "ISIC17: Woche zwei", "url": "/announcements/2017/isic17-woche-zwei/"}, {"date": "11/02/2017", "isodate": "2017-11-02T09:02:53+01:00", "title": "ISIC17: Erster Zwischenstand!", "url": "/announcements/2017/isic17-woche-eins/"}, {"date": "10/27/2017", "isodate": "2017-10-27T23:37:28+02:00", "title": "ISIC17: \"Operation Dauerwelle\" hat begonnen!", "url": "/announcements/2017/operation-dauerwelle-hat-begonnen/"}, {"date": "10/11/2017", "isodate": "2017-10-11T10:09:36+02:00", "title": "ISIC17: Plakat und Kick-off Event", "url": "/announcements/2017/isic17-plakat-und-kick-off-event/"}, {"date": "10/08/2017", "isodate": "2017-10-08T00:22:09+02:00", "title": "ISIC17: Tolle Preise zu gewinnen!", "url": "/announcements/2017/isic17-tolle-preise-zu-gewinnen/"}, {"date": "09/06/2017", "isodate": "2017-09-06T22:00:54+02:00", "title": "Die IEEE Signal Intelligence Challenge 2017 naht!", "url": "/announcements/2017/die-ieee-signal-intelligence-challenge-2017-naht/"}, {"date": "10/17/2016", "isodate": "2016-10-17T12:37:04+02:00", "title": "Upcoming: Signal Intelligence Challenge 2016", "url": "/announcements/2016/upcoming-signal-intelligence-challenge-2016/"}]}]}